setup.py
responsive_content_type/__init__.py
responsive_content_type/admin.py
responsive_content_type/models.py
responsive_content_type.egg-info/PKG-INFO
responsive_content_type.egg-info/SOURCES.txt
responsive_content_type.egg-info/dependency_links.txt
responsive_content_type.egg-info/top_level.txt