Metadata-Version: 1.1
Name: responsive-content-type
Version: 0.0.1
Summary: Add responsiveness to the FeinCMS content types
Home-page: https://github.com/Sytzeandreae/FeinCMS-Responsive-Content-Type
Author: Sytzeandreae
Author-email: sytzeandreae@gmail.com
License: GNU-GPL
Keywords: responsive feincms contenttype content type
Platform: UNKNOWN
Classifier: Development Status :: 4 - Beta
Classifier: Intended Audience :: Developers
Classifier: License :: OSI Approved :: GNU General Public License v3 (GPLv3)
Classifier: Programming Language :: Python :: 2
Classifier: Programming Language :: Python :: 2.7
Classifier: Framework :: Django
Classifier: Topic :: Internet
Classifier: Topic :: Internet :: WWW/HTTP :: Dynamic Content
Classifier: Topic :: Internet :: WWW/HTTP :: Site Management
